{"Blog": [2, "/categories/blog.html", {"posts": [{"date": "05/08/2014", "url": "\\posts\\missing-the-point.html", "isodate": "2014-05-08T07:36:12+00:00", "title": "Missing The Point"}, {"date": "05/06/2014", "url": "\\posts\\moved-on.html", "isodate": "2014-05-06T13:36:08+00:00", "title": "Moved On"}]}], "new release": [1, "/categories/new-release.html", {"posts": [{"date": "06/14/2014", "url": "\\posts\\knockn-boots.html", "isodate": "2014-06-14T11:20:43+00:00", "title": "Knock'n Boots"}]}], "games": [1, "/categories/games.html", {"posts": [{"date": "11/01/2013", "url": "\\posts\\kill-orcs-build-a-better-marriage.html", "isodate": "2013-11-01T18:47:42+00:00", "title": "Kill Orcs & Build A Better Marriage"}]}], "Card Games": [1, "/categories/card-games.html", {"posts": [{"date": "05/30/2014", "url": "\\posts\\more-serving-more-purpose.html", "isodate": "2014-05-30T13:19:15+00:00", "title": "More Serving, More Purpose"}]}], "indie": [1, "/categories/indie.html", {"posts": [{"date": "11/01/2013", "url": "\\posts\\kill-orcs-build-a-better-marriage.html", "isodate": "2013-11-01T18:47:42+00:00", "title": "Kill Orcs & Build A Better Marriage"}]}], "collaboration": [1, "/categories/collaboration.html", {"posts": [{"date": "06/24/2014", "url": "\\posts\\dance-floor-for-your-feet.html", "isodate": "2014-06-24T12:47:08+00:00", "title": "Dance Floor For Your Feet"}]}], "Update": [7, "/categories/update.html", {"posts": [{"date": "06/24/2014", "url": "\\posts\\dance-floor-for-your-feet.html", "isodate": "2014-06-24T12:47:08+00:00", "title": "Dance Floor For Your Feet"}, {"date": "06/14/2014", "url": "\\posts\\knockn-boots.html", "isodate": "2014-06-14T11:20:43+00:00", "title": "Knock'n Boots"}, {"date": "05/30/2014", "url": "\\posts\\more-serving-more-purpose.html", "isodate": "2014-05-30T13:19:15+00:00", "title": "More Serving, More Purpose"}, {"date": "05/23/2014", "url": "\\posts\\a-strange-dance.html", "isodate": "2014-05-23T08:42:36+00:00", "title": "A Strange Dance"}, {"date": "05/13/2014", "url": "\\posts\\you-shouldve-seen-this-coming.html", "isodate": "2014-05-13T15:28:57+00:00", "title": "You should've seen this coming"}, {"date": "05/08/2014", "url": "\\posts\\missing-the-point.html", "isodate": "2014-05-08T07:36:12+00:00", "title": "Missing The Point"}, {"date": "05/06/2014", "url": "\\posts\\moved-on.html", "isodate": "2014-05-06T13:36:08+00:00", "title": "Moved On"}]}], "jerks": [1, "/categories/jerks.html", {"posts": [{"date": "05/08/2014", "url": "\\posts\\missing-the-point.html", "isodate": "2014-05-08T07:36:12+00:00", "title": "Missing The Point"}]}], "instrumental": [1, "/categories/instrumental.html", {"posts": [{"date": "05/23/2014", "url": "\\posts\\a-strange-dance.html", "isodate": "2014-05-23T08:42:36+00:00", "title": "A Strange Dance"}]}], "rant": [1, "/categories/rant.html", {"posts": [{"date": "05/08/2014", "url": "\\posts\\missing-the-point.html", "isodate": "2014-05-08T07:36:12+00:00", "title": "Missing The Point"}]}], "couples": [1, "/categories/couples.html", {"posts": [{"date": "11/01/2013", "url": "\\posts\\kill-orcs-build-a-better-marriage.html", "isodate": "2013-11-01T18:47:42+00:00", "title": "Kill Orcs & Build A Better Marriage"}]}], "Facebook": [1, "/categories/facebook.html", {"posts": [{"date": "05/13/2014", "url": "\\posts\\you-shouldve-seen-this-coming.html", "isodate": "2014-05-13T15:28:57+00:00", "title": "You should've seen this coming"}]}], "dance": [2, "/categories/dance.html", {"posts": [{"date": "06/24/2014", "url": "\\posts\\dance-floor-for-your-feet.html", "isodate": "2014-06-24T12:47:08+00:00", "title": "Dance Floor For Your Feet"}, {"date": "05/23/2014", "url": "\\posts\\a-strange-dance.html", "isodate": "2014-05-23T08:42:36+00:00", "title": "A Strange Dance"}]}], "news": [2, "/categories/news.html", {"posts": [{"date": "05/13/2014", "url": "\\posts\\you-shouldve-seen-this-coming.html", "isodate": "2014-05-13T15:28:57+00:00", "title": "You should've seen this coming"}, {"date": "05/06/2014", "url": "\\posts\\moved-on.html", "isodate": "2014-05-06T13:36:08+00:00", "title": "Moved On"}]}], "music": [7, "/categories/music.html", {"posts": [{"date": "06/24/2014", "url": "\\posts\\dance-floor-for-your-feet.html", "isodate": "2014-06-24T12:47:08+00:00", "title": "Dance Floor For Your Feet"}, {"date": "06/14/2014", "url": "\\posts\\knockn-boots.html", "isodate": "2014-06-14T11:20:43+00:00", "title": "Knock'n Boots"}, {"date": "05/30/2014", "url": "\\posts\\more-serving-more-purpose.html", "isodate": "2014-05-30T13:19:15+00:00", "title": "More Serving, More Purpose"}, {"date": "05/23/2014", "url": "\\posts\\a-tasty-sample.html", "isodate": "2014-05-23T11:36:30+00:00", "title": "A Tasty Sample"}, {"date": "05/23/2014", "url": "\\posts\\a-strange-dance.html", "isodate": "2014-05-23T08:42:36+00:00", "title": "A Strange Dance"}, {"date": "05/13/2014", "url": "\\posts\\you-shouldve-seen-this-coming.html", "isodate": "2014-05-13T15:28:57+00:00", "title": "You should've seen this coming"}, {"date": "05/08/2014", "url": "\\posts\\missing-the-point.html", "isodate": "2014-05-08T07:36:12+00:00", "title": "Missing The Point"}]}], "MTG": [1, "/categories/mtg.html", {"posts": [{"date": "05/30/2014", "url": "\\posts\\more-serving-more-purpose.html", "isodate": "2014-05-30T13:19:15+00:00", "title": "More Serving, More Purpose"}]}], "Soundcloud": [2, "/categories/soundcloud.html", {"posts": [{"date": "05/30/2014", "url": "\\posts\\more-serving-more-purpose.html", "isodate": "2014-05-30T13:19:15+00:00", "title": "More Serving, More Purpose"}, {"date": "05/23/2014", "url": "\\posts\\a-tasty-sample.html", "isodate": "2014-05-23T11:36:30+00:00", "title": "A Tasty Sample"}]}]}